{
    "Id": "Wode Native",
    "Table": [
        {
            "SuccessRange": [ 1 ],
            "Description": "Tiefling",
            "Link": {
                "Default": "Folk Relationships"
            }
        },
        {
            "SuccessRange": [ 2 ],
            "Description": "Elf",
            "Link": {
                "Default": "Folk Relationships"
            }
        },
        {
            "SuccessRange": [ 3 ],
            "Description": "Human",
            "Link": {
                "Default": "Folk Relationships"
            }
        },
        {
            "SuccessRange": [ 4 ],
            "Description": "Changeling",
            "Link": {
                "Default": "Folk Relationships"
            }
        },
        {
            "SuccessRange": [ 5 ],
            "Description": "Demifey",
            "Link": {
                "Default": "Folk Relationships"
            }
        },
        {
            "SuccessRange": [ 6 ],
            "Description": "Angulotls",
            "Link": {
                "Default": "Folk Relationships"
            }
        },
        {
            "SuccessRange": [ 7 ],
            "Description": "Genasi",
            "Link": {
                "Default": "Folk Relationships"
            }
        },
        {
            "SuccessRange": [ 8, 10 ],
            "Description": "Goblin",
            "Link": {
                "Default": "Folk Relationships"
            }
        },
        {
            "SuccessRange": [ 11,12 ],
            "Description": "Specific character",
            "Link": {
                "Default": "Specific Wode Native"
            }
        }
    ]
}
